timeit_compare/__init__.py
timeit_compare/__init__.pyi
timeit_compare/__main__.py
timeit_compare/__main__.pyi
timeit_compare/_output.py
timeit_compare-1.4.3.dist-info/LICENSE
timeit_compare-1.4.3.dist-info/METADATA
timeit_compare-1.4.3.dist-info/WHEEL
timeit_compare-1.4.3.dist-info/top_level.txt
timeit_compare-1.4.3.dist-info/RECORD
