Metadata-Version: 2.2
Name: timeit_compare
Version: 1.4.3
Summary: Conveniently measure and compare the execution times of multiple statements.
Author-email: Liu Wei <23S112099@stu.hit.edu.cn>
Maintainer-email: Liu Wei <23S112099@stu.hit.edu.cn>
License: MIT License
Project-URL: Homepage, https://github.com/AomandeNiuma/timeit_compare
Keywords: timeit_compare,timeit,performance
Classifier: License :: OSI Approved :: MIT License
Classifier: Programming Language :: Python :: 3
Classifier: Programming Language :: Python :: 3.6
Classifier: Programming Language :: Python :: 3.7
Classifier: Programming Language :: Python :: 3.8
Classifier: Programming Language :: Python :: 3.9
Classifier: Programming Language :: Python :: 3.10
Classifier: Programming Language :: Python :: 3.11
Classifier: Programming Language :: Python :: 3.12
Classifier: Programming Language :: Python :: 3.13
Requires-Python: >=3.6.0
License-File: LICENSE
Requires-Dist: typing_extensions
